realms_cli/__init__.py
realms_cli/constants.py
realms_cli/logging_config.py
realms_cli/main.py
realms_cli/models.py
realms_cli/utils.py
realms_cli/commands/__init__.py
realms_cli/commands/create.py
realms_cli/commands/db.py
realms_cli/commands/deploy.py
realms_cli/commands/export_data.py
realms_cli/commands/extension.py
realms_cli/commands/import_data.py
realms_cli/commands/init.py
realms_cli/commands/ps.py
realms_cli/commands/registry.py
realms_cli/commands/run.py
realms_cli/commands/self_register.py
realms_cli/commands/shell.py
realms_cli-0.1.4.dist-info/licenses/LICENSE
realms_cli-0.1.4.dist-info/METADATA
realms_cli-0.1.4.dist-info/WHEEL
realms_cli-0.1.4.dist-info/entry_points.txt
realms_cli-0.1.4.dist-info/top_level.txt
realms_cli-0.1.4.dist-info/RECORD
