Metadata-Version: 2.4
Name: realms-cli
Version: 0.1.4
Summary: CLI tool for managing Realms project lifecycle
Author-email: Realms Team <team@realms.dev>
License: MIT
Project-URL: Homepage, https://github.com/smartsocialcontracts/realms
Project-URL: Repository, https://github.com/smartsocialcontracts/realms
Project-URL: Documentation, https://docs.realms.dev
Project-URL: Bug Tracker, https://github.com/smartsocialcontracts/realms/issues
Keywords: realms,cli,internet-computer,dfx,blockchain
Classifier: Development Status :: 4 - Beta
Classifier: Intended Audience :: Developers
Classifier: License :: OSI Approved :: MIT License
Classifier: Operating System :: OS Independent
Classifier: Programming Language :: Python :: 3.10
Classifier: Topic :: Software Development :: Libraries :: Python Modules
Classifier: Topic :: System :: Systems Administration
Requires-Python: >=3.8
License-File: LICENSE
Requires-Dist: typer[all]>=0.9.0
Requires-Dist: rich>=13.0.0
Requires-Dist: pydantic>=2.0.0
Requires-Dist: jsonschema>=4.0.0
Requires-Dist: jinja2>=3.0.0
Requires-Dist: gitpython>=3.1.0
Requires-Dist: requests>=2.28.0
Requires-Dist: click>=8.0.0
Requires-Dist: prompt-toolkit>=3.0.0
Requires-Dist: kybra==0.7.*
Requires-Dist: kybra-simple-logging==0.2.*
Requires-Dist: kybra-simple-db>=0.4.0
Provides-Extra: dev
Requires-Dist: pytest>=7.0.0; extra == "dev"
Requires-Dist: pytest-cov>=4.0.0; extra == "dev"
Requires-Dist: black>=23.0.0; extra == "dev"
Requires-Dist: isort>=5.12.0; extra == "dev"
Requires-Dist: flake8>=6.0.0; extra == "dev"
Requires-Dist: mypy>=1.0.0; extra == "dev"
Requires-Dist: build>=0.10.0; extra == "dev"
Requires-Dist: twine>=4.0.0; extra == "dev"
Dynamic: license-file
